rospy_message_converter/__init__.py
rospy_message_converter/json_message_converter.py
rospy_message_converter/message_converter.py
rospy_message_converter-0.5.2.dist-info/METADATA
rospy_message_converter-0.5.2.dist-info/WHEEL
rospy_message_converter-0.5.2.dist-info/top_level.txt
rospy_message_converter-0.5.2.dist-info/RECORD
